notemgmt/__init__.py
notemgmt/create_answer_note.py
notemgmt/create_lecture_note.py
notemgmt-2.0.0.dist-info/LICENSE
notemgmt-2.0.0.dist-info/METADATA
notemgmt-2.0.0.dist-info/WHEEL
notemgmt-2.0.0.dist-info/entry_points.txt
notemgmt-2.0.0.dist-info/top_level.txt
notemgmt-2.0.0.dist-info/RECORD
