Metadata-Version: 2.1
Name: notemgmt
Version: 2.0.0
Summary: a note management tool
Home-page: https://github.com/VinitraMk/notemgmt
Author: Vinitra Muralikrishnan
Author-email: vinitramk@gmail.com
License: GNU
License-File: LICENSE
